CHANGES.rst
LICENSE
MANIFEST.in
README.rst
VERSION
requirements-dev.txt
requirements.txt
setup.cfg
setup.py
molo/__init__.py
molo.yourwords.egg-info/PKG-INFO
molo.yourwords.egg-info/SOURCES.txt
molo.yourwords.egg-info/dependency_links.txt
molo.yourwords.egg-info/namespace_packages.txt
molo.yourwords.egg-info/not-zip-safe
molo.yourwords.egg-info/requires.txt
molo.yourwords.egg-info/top_level.txt
molo/yourwords/__init__.py
molo/yourwords/admin.py
molo/yourwords/forms.py
molo/yourwords/models.py
molo/yourwords/urls.py
molo/yourwords/views.py
molo/yourwords/wagtail_hooks.py
molo/yourwords/migrations/0001_initial.py
molo/yourwords/migrations/0002_yourwordscompetitionentry_submission_date.py
molo/yourwords/migrations/0003_auto_20151119_1352.py
molo/yourwords/migrations/0004_yourwordscompetitionentry_article_page.py
molo/yourwords/migrations/0005_your_words_competition_indexPage.py
molo/yourwords/migrations/0006_create_your_words_index_pages.py
molo/yourwords/migrations/0007_add_yourwords_permission_to_groups.py
molo/yourwords/migrations/0008_add_can_view_entry_permission.py
molo/yourwords/migrations/0009_add_translation_fields.py
molo/yourwords/migrations/__init__.py
molo/yourwords/templates/admin/yourwords/model_admin_competition_template.html
molo/yourwords/templates/admin/yourwords/model_admin_template.html
molo/yourwords/templates/admin/yourwords/yourwords_date_range_filter.html
molo/yourwords/templates/admin/yourwords/yourwordscompetitionentry/change_form.html
molo/yourwords/templates/yourwords/terms_and_conditions.html
molo/yourwords/templates/yourwords/thank_you.html
molo/yourwords/templates/yourwords/your_words_competition.html
molo/yourwords/templates/yourwords/your_words_competition_entry.html
molo/yourwords/templates/yourwords/your_words_competition_tag.html
molo/yourwords/templates/yourwords/your_words_competition_tag_for_section.html
molo/yourwords/templatetags/__init__.py
molo/yourwords/templatetags/competition_tag.py
molo/yourwords/test_templates/section_listing_homepage.html
molo/yourwords/test_templates/section_page.html
molo/yourwords/tests/__init__.py
molo/yourwords/tests/base.py
molo/yourwords/tests/test_admin_actions.py
molo/yourwords/tests/test_views.py
molo/yourwords/tests/test_wagtail_admin_action.py