Metadata-Version: 1.1
Name: molo.yourwords
Version: 8.1.0
Summary: A Molo module that enables user generated content competitions
Home-page: http://github.com/praekelt/molo.yourwords
Author: Praekelt Foundation
Author-email: dev@praekelt.com
License: BSD
Keywords: praekelt,mobi,web,django
Platform: UNKNOWN
Classifier: Programming Language :: Python :: 2.7
Classifier: Programming Language :: Python :: 3.6
Classifier: Framework :: Django
Classifier: Topic :: Internet :: WWW/HTTP
Classifier: Topic :: Internet :: WWW/HTTP :: WSGI :: Application
